dodil/__init__.py
dodil/client.py
dodil/vspace.py
dodil/auth/__init__.py
dodil/auth/authorization.py
dodil/common/__init__.py
dodil/common/dns_utils.py
dodil/transport/__init__.py
dodil/transport/common.py
dodil/transport/grpc.py
dodil/transport/http.py
dodil/vbase/__init__.py
dodil/vbase/vbase_client.py
dodil/vng/__init__.py
dodil/vng/vng_client.py
dodil/vng/v1/vng_pb2.py
dodil/vng/v1/vng_pb2_grpc.py
dodil-0.0.8.dist-info/METADATA
dodil-0.0.8.dist-info/WHEEL
dodil-0.0.8.dist-info/RECORD
