Metadata-Version: 2.4
Name: dodil
Version: 0.0.8
Summary: DODIL Python SDK
Project-URL: Repository, https://github.com/dodilio/sdk-dodil-python
Author-email: DODIL <support@dodil.io>
Classifier: Programming Language :: Python :: 3
Classifier: Programming Language :: Python :: 3.10
Classifier: Programming Language :: Python :: 3.11
Classifier: Programming Language :: Python :: 3.12
Classifier: Programming Language :: Python :: 3.13
Classifier: Programming Language :: Python :: 3.14
Requires-Python: <4.0,>=3.10
Requires-Dist: grpcio-tools<2,>=1.76.0
Requires-Dist: grpcio<2,>=1.76.0
Requires-Dist: httpx<0.28,>=0.27.0
Requires-Dist: plotly<6,>=5.20.0
Requires-Dist: pydantic-settings<3,>=2.12.0
Requires-Dist: pydantic<3,>=2.12.5
Requires-Dist: pymilvus<3,>=2.6.6
Requires-Dist: scikit-learn<2,>=1.3.0
Requires-Dist: tqdm<5,>=4.65.0
